pvct/__init__.py
pvct/__main__.py
pvct/cli.py
pvct/pvct.py
pvct-0.0.0.dist-info/AUTHORS.rst
pvct-0.0.0.dist-info/LICENSE
pvct-0.0.0.dist-info/METADATA
pvct-0.0.0.dist-info/WHEEL
pvct-0.0.0.dist-info/entry_points.txt
pvct-0.0.0.dist-info/top_level.txt
pvct-0.0.0.dist-info/RECORD
